malpolon/__init__.py
malpolon/check_install.py
malpolon/logging.py
malpolon/data/__init__.py
malpolon/data/data_module.py
malpolon/data/environmental_raster.py
malpolon/data/get_jpeg_patches_stats.py
malpolon/data/utils.py
malpolon/data/datasets/__init__.py
malpolon/data/datasets/_base.py
malpolon/data/datasets/geolifeclef2022.py
malpolon/data/datasets/geolifeclef2023.py
malpolon/data/datasets/geolifeclef2024.py
malpolon/data/datasets/geolifeclef2024_pre_extracted.py
malpolon/data/datasets/torchgeo_concat.py
malpolon/data/datasets/torchgeo_datasets.py
malpolon/data/datasets/torchgeo_sentinel2.py
malpolon/data/datasets/_data/__init__.py
malpolon/data/datasets/_data/minigeolifeclef2022_species_details.csv
malpolon/models/__init__.py
malpolon/models/model_builder.py
malpolon/models/standard_prediction_systems.py
malpolon/models/utils.py
malpolon/models/custom_models/__init__.py
malpolon/models/custom_models/glc2024_multimodal_ensemble_model.py
malpolon/models/custom_models/glc2024_multimodal_ensemble_model_modality_specific.py
malpolon/models/custom_models/glc2024_pre_extracted_prediction_system.py
malpolon/models/custom_models/multi_modal.py
malpolon/plot/__init__.py
malpolon/plot/history.py
malpolon/plot/map.py
malpolon-2.1.2.dist-info/LICENSE.md
malpolon-2.1.2.dist-info/METADATA
malpolon-2.1.2.dist-info/WHEEL
malpolon-2.1.2.dist-info/top_level.txt
malpolon-2.1.2.dist-info/RECORD
