Metadata-Version: 2.1
Name: malpolon
Version: 2.1.2
Summary: Malpolon v2.1.2
Home-page: https://github.com/plantnet/malpolon
Author: Theo Larcher, Titouan Lorieul, Benjamin Deneu, Lukas Picek
Author-email: theo.larcher@inria.fr, titouan.lorieul@gmail.com, benjamin.deneu@wsl.ch, lukas.picek@inria.fr
Project-URL: Bug Reports, https://github.com/plantnet/malpolon/issues/new?assignees=aerodynamic-sauce-pan&labels=bug&projects=&template=bug_report.md&title=%5BBUG%5D
Project-URL: Feature request, https://github.com/plantnet/malpolon/issues/new?assignees=aerodynamic-sauce-pan&labels=enhancement&projects=&template=enhancement.md&title=%5BEnhancement%5D
Project-URL: Host organizer, https://plantnet.org/
Project-URL: Source, https://github.com/plantnet/malpolon
Classifier: Development Status :: 4 - Beta
Classifier: Intended Audience :: Science/Research
Classifier: License :: OSI Approved :: MIT License
Classifier: Programming Language :: Python :: 3.10
Classifier: Environment :: GPU :: NVIDIA CUDA
Classifier: Operating System :: Unix
Classifier: Operating System :: MacOS
Classifier: Typing :: Typed
Classifier: Topic :: Scientific/Engineering
Classifier: Topic :: Scientific/Engineering :: Artificial Intelligence
Classifier: Topic :: Scientific/Engineering :: Image Processing
Classifier: Topic :: Scientific/Engineering :: Image Recognition
Classifier: Topic :: Scientific/Engineering :: GIS
Requires-Python: >=3.10, <4
License-File: LICENSE.md
Requires-Dist: Cartopy>=0.22.0
Requires-Dist: kaggle>=1.5.16
Requires-Dist: matplotlib>=3.8.0
Requires-Dist: numpy>=1.26.4
Requires-Dist: omegaconf>=2.3.0
Requires-Dist: pandas>=2.2.1
Requires-Dist: Pillow>=10.3.0
Requires-Dist: planetary_computer>=1.0.0
Requires-Dist: pyproj>=3.6.1
Requires-Dist: pystac>=1.6.1
Requires-Dist: pytest>=7.2.2
Requires-Dist: pytorch_lightning>=2.3.3
Requires-Dist: rasterio>=1.3.8.post1
Requires-Dist: scikit_learn>=1.5.0
Requires-Dist: Shapely>=2.0.3
Requires-Dist: tifffile>=2022.10.10
Requires-Dist: timm>=0.9.2
Requires-Dist: torch>=2.2.0
Requires-Dist: torchgeo>=0.5.0
Requires-Dist: torchmetrics>=1.2.0
Requires-Dist: torchvision>=0.17.0
Requires-Dist: tqdm>=4.66.3
Requires-Dist: verde>=1.8.0
